odoo/addons/base_fontawesome/README.rst
odoo/addons/base_fontawesome/__init__.py
odoo/addons/base_fontawesome/__manifest__.py
odoo/addons/base_fontawesome/i18n/base_fontawesome.pot
odoo/addons/base_fontawesome/i18n/es_ES.po
odoo/addons/base_fontawesome/i18n/zh_CN.po
odoo/addons/base_fontawesome/readme/CONTRIBUTORS.rst
odoo/addons/base_fontawesome/readme/DESCRIPTION.rst
odoo/addons/base_fontawesome/readme/USAGE.rst
odoo/addons/base_fontawesome/static/description/icon.png
odoo/addons/base_fontawesome/static/description/index.html
odoo/addons/base_fontawesome/static/lib/fontawesome-5.15.3/css/all.css
odoo/addons/base_fontawesome/static/lib/fontawesome-5.15.3/css/v4-shims.css
odoo/addons/base_fontawesome/static/lib/fontawesome-5.15.3/webfonts/fa-brands-400.eot
odoo/addons/base_fontawesome/static/lib/fontawesome-5.15.3/webfonts/fa-brands-400.svg
odoo/addons/base_fontawesome/static/lib/fontawesome-5.15.3/webfonts/fa-brands-400.ttf
odoo/addons/base_fontawesome/static/lib/fontawesome-5.15.3/webfonts/fa-brands-400.woff
odoo/addons/base_fontawesome/static/lib/fontawesome-5.15.3/webfonts/fa-brands-400.woff2
odoo/addons/base_fontawesome/static/lib/fontawesome-5.15.3/webfonts/fa-regular-400.eot
odoo/addons/base_fontawesome/static/lib/fontawesome-5.15.3/webfonts/fa-regular-400.svg
odoo/addons/base_fontawesome/static/lib/fontawesome-5.15.3/webfonts/fa-regular-400.ttf
odoo/addons/base_fontawesome/static/lib/fontawesome-5.15.3/webfonts/fa-regular-400.woff
odoo/addons/base_fontawesome/static/lib/fontawesome-5.15.3/webfonts/fa-regular-400.woff2
odoo/addons/base_fontawesome/static/lib/fontawesome-5.15.3/webfonts/fa-solid-900.eot
odoo/addons/base_fontawesome/static/lib/fontawesome-5.15.3/webfonts/fa-solid-900.svg
odoo/addons/base_fontawesome/static/lib/fontawesome-5.15.3/webfonts/fa-solid-900.ttf
odoo/addons/base_fontawesome/static/lib/fontawesome-5.15.3/webfonts/fa-solid-900.woff
odoo/addons/base_fontawesome/static/lib/fontawesome-5.15.3/webfonts/fa-solid-900.woff2
odoo12_addon_base_fontawesome-12.0.5.16.0.dist-info/METADATA
odoo12_addon_base_fontawesome-12.0.5.16.0.dist-info/WHEEL
odoo12_addon_base_fontawesome-12.0.5.16.0.dist-info/top_level.txt
odoo12_addon_base_fontawesome-12.0.5.16.0.dist-info/RECORD
