Metadata-Version: 2.1
Name: odoo12-addon-base-fontawesome
Version: 12.0.5.16.0
Summary: Up to date Fontawesome resources.
Home-page: https://github.com/OCA/server-tools
Author: Camptocamp,Creu Blanca,Odoo Community Association (OCA)
Author-email: support@odoo-community.org
License: LGPL-3
Platform: UNKNOWN
Classifier: Programming Language :: Python
Classifier: Framework :: Odoo
Classifier: Framework :: Odoo :: 12.0
Classifier: License :: OSI Approved :: GNU Lesser General Public License v3 (LGPLv3)
Requires-Python: >=3.5
Requires-Dist: odoo (<12.1dev,>=12.0a)
